{
  "shape": {
    "M": 1,
    "N": 4096,
    "K": 7168
  },
  "gpu": "AMD Instinct MI355X",
  "baseline_unified": {
    "ms": 0.048462890554219484,
    "tflops": 1.2116540166811707
  },
  "best": {
    "kernelId": 14,
    "splitK": 2,
    "tile": "32x128x128"
  },
  "best_tflops": 4.236511259613276,
  "all_results": [
    {
      "kernelId": 14,
      "splitK": 2,
      "ms": 0.01386052164189461,
      "tflops": 4.236511259613276,
      "tile": "32x128x128"
    },
    {
      "kernelId": 12,
      "splitK": 2,
      "ms": 0.014178589121119616,
      "tflops": 4.141473844709532,
      "tile": "64x128x128"
    },
    {
      "kernelId": 13,
      "splitK": 2,
      "ms": 0.01440019886486917,
      "tflops": 4.077739241730499,
      "tile": "96x128x128"
    },
    {
      "kernelId": 0,
      "splitK": 2,
      "ms": 0.014575268567376317,
      "tflops": 4.028759794617644,
      "tile": "64x128x128"
    },
    {
      "kernelId": 4,
      "splitK": 2,
      "ms": 0.01471634075055905,
      "tflops": 3.9901397361819932,
      "tile": "96x128x128"
    },
    {
      "kernelId": 8,
      "splitK": 2,
      "ms": 0.014882985874378371,
      "tflops": 3.9454620528189284,
      "tile": "128x128x128"
    },
    {
      "kernelId": 15,
      "splitK": 2,
      "ms": 0.015177889684079971,
      "tflops": 3.8688023975817565,
      "tile": "32x256x128"
    },
    {
      "kernelId": 1,
      "splitK": 2,
      "ms": 0.015868276110234433,
      "tflops": 3.7004811103663413,
      "tile": "64x256x128"
    },
    {
      "kernelId": 5,
      "splitK": 2,
      "ms": 0.01714573629179049,
      "tflops": 3.424773074814857,
      "tile": "96x256x128"
    },
    {
      "kernelId": 14,
      "splitK": 1,
      "ms": 0.018018315781158024,
      "tflops": 3.2589203515571916,
      "tile": "32x128x128"
    },
    {
      "kernelId": 9,
      "splitK": 2,
      "ms": 0.018571236229915272,
      "tflops": 3.161892685712065,
      "tile": "128x256x128"
    },
    {
      "kernelId": 12,
      "splitK": 1,
      "ms": 0.018821235665501562,
      "tflops": 3.1198937754991007,
      "tile": "64x128x128"
    },
    {
      "kernelId": 0,
      "splitK": 1,
      "ms": 0.018991122907545642,
      "tflops": 3.0919844121839155,
      "tile": "64x128x128"
    },
    {
      "kernelId": 13,
      "splitK": 1,
      "ms": 0.019514415361112057,
      "tflops": 3.0090707260959797,
      "tile": "96x128x128"
    },
    {
      "kernelId": 4,
      "splitK": 1,
      "ms": 0.019692547438347766,
      "tflops": 2.9818516971376012,
      "tile": "96x128x128"
    },
    {
      "kernelId": 16,
      "splitK": 2,
      "ms": 0.01982158237934518,
      "tflops": 2.962440378180335,
      "tile": "32x384x128"
    },
    {
      "kernelId": 15,
      "splitK": 1,
      "ms": 0.020084593024165293,
      "tflops": 2.9236467938060393,
      "tile": "32x256x128"
    },
    {
      "kernelId": 8,
      "splitK": 1,
      "ms": 0.0201070937099603,
      "tflops": 2.9203751097510526,
      "tile": "128x128x128"
    },
    {
      "kernelId": 2,
      "splitK": 2,
      "ms": 0.021174592277969355,
      "tflops": 2.773146950323772,
      "tile": "64x384x128"
    },
    {
      "kernelId": 6,
      "splitK": 2,
      "ms": 0.022044292443115225,
      "tflops": 2.66373965739777,
      "tile": "96x384x128"
    }
  ]
}